baidu/__init__.py
baidu/client.py
baidu/exceptions.py
baidu/api/__init__.py
baidu/api/base.py
baidu/api/geoconv.py
baidu/api/iplocation.py
baidu/api/map/__init__.py
baidu/api/map/geosearch.py
baidu/api/map/lbscloud.py
baidu/models/__init__.py
baidu/models/lbscloud.py
baidupy-0.0.5.dist-info/DESCRIPTION.rst
baidupy-0.0.5.dist-info/METADATA
baidupy-0.0.5.dist-info/RECORD
baidupy-0.0.5.dist-info/WHEEL
baidupy-0.0.5.dist-info/metadata.json
baidupy-0.0.5.dist-info/pbr.json
baidupy-0.0.5.dist-info/top_level.txt
